album/__init__.py
album/docker_plugin/__init__.py
album/docker_plugin/argument_parsing.py
album/docker_plugin/build_image.py
album/docker_plugin/solution_entrypoint.sh
album_docker-0.2.0.dist-info/licenses/LICENSE
album_docker-0.2.0.dist-info/METADATA
album_docker-0.2.0.dist-info/WHEEL
album_docker-0.2.0.dist-info/entry_points.txt
album_docker-0.2.0.dist-info/top_level.txt
album_docker-0.2.0.dist-info/RECORD
